Phinder/__init__.py
Phinder/PharmacoFindWorkplace/POpt2.py
Phinder/PharmacoFindWorkplace/PharmacoFindWithTanimoto.py
Phinder/PharmacoFindWorkplace/__init__.py
Phinder/docking/__init__.py
Phinder/docking/docker.py
Phinder-0.0.3.dist-info/METADATA
Phinder-0.0.3.dist-info/WHEEL
Phinder-0.0.3.dist-info/entry_points.txt
Phinder-0.0.3.dist-info/top_level.txt
Phinder-0.0.3.dist-info/RECORD
