Metadata-Version: 2.1
Name: Phinder
Version: 0.0.3
Summary: UNKNOWN
Home-page: https://github.com/gnina/phinder
Author: Dillon Gavlock & Samuel Cho
Author-email: dcg33@pitt.edu
License: MIT
Platform: UNKNOWN
Classifier: License :: OSI Approved :: MIT License
Classifier: Programming Language :: Python
Classifier: Programming Language :: Python :: 2
Classifier: Programming Language :: Python :: 3
Requires-Dist: numpy
Requires-Dist: pandas
Requires-Dist: scipy
